[
    {
        "name": "【鳴海】",
        "message": "「珍しい。ずいぶんと長電話だったじゃねーか」"
    },
    {
        "name": "【瑠依】",
        "message": "「望んでしていたわけじゃないよ。切るタイミングがなかった」"
    },
    {
        "name": "【鳴海】",
        "message": "「いきなり切らないあたり、一応は渋谷のことダチだって認めてるんだな」"
    },
    {
        "name": "【瑠依】",
        "message": "「あいつは突き抜けてるから。どんな方向に伸びていようが、直線に伸びてる奴にはやっぱり一目置くよ」"
    },
    {
        "message": "手元の携帯を見て、電話口の渋谷の様子を思い返す。"
    },
    {
        "message": "目を塞げば吐息がかかりそうなほどリアリティのある濡れた声。"
    },
    {
        "message": "俺は渋谷に従うまま、雑音のように入ってくる雄叫びを無視し、耳を傾けた。"
    },
    {
        "message": "おそらく渋谷は声の主と交尾に励んでいたのだろう。"
    },
    {
        "message": "昼間から。獣のように。快楽だけを求める。"
    },
    {
        "message": "誰と何をしようが渋谷の勝手だし、その方向性が間違っていても何一つ助言なんて与えるつもりはない。"
    },
    {
        "message": "ただ、最後まで聞いて欲しいという一生のお願いに付き合っただけだ。"
    },
    {
        "name": "【ヴィヴィ】",
        "message": "「……じゃ」"
    },
    {
        "name": "【瑠依】",
        "message": "「ん？　俺を守らなくていいのか？」"
    },
    {
        "name": "【ヴィヴィ】",
        "message": "「言いつけを守っていた。問題ない」"
    },
    {
        "message": "言われたことの意味を少しだけ考える。"
    },
    {
        "message": "ヴィヴィの教室での行動から、今の言葉を理解した。"
    },
    {
        "name": "【瑠依】",
        "message": "「さすがに学園で肌身離さずとはいかないけどな」"
    },
    {
        "message": "言いつけ――武器を所持するという約束のことだろう。"
    },
    {
        "message": "刀は、竹刀袋に入れた状態で掃除用具入れの中を立てかけてある。"
    },
    {
        "message": "箒に埋もれているため、帰りのホームルームまではよほどの事がない限り見つからないだろう。"
    },
    {
        "message": "つまりあの時、ヴィヴィは刀の隠し場所を直感し、確認するために用具入れに入ったのか。"
    },
    {
        "name": "【ヴィヴィ】",
        "message": "「自分の身は自分で守れ。私は狩りに出る」"
    },
    {
        "name": "【瑠依】",
        "message": "「お、おい、ここでそんな話は……」"
    },
    {
        "name": "【鳴海】",
        "message": "「ブツクサ独り言ほざくな。うるせーぞ」"
    },
    {
        "name": "【瑠依】",
        "message": "「あ、ああ……そうだな」"
    },
    {
        "message": "“独り言”――鳴海には俺がそういうふうに見えているのだ。"
    },
    {
        "message": "重要な話をしている今は“認識の外”。条件は不明だが、器用に使い分けていたらしい。"
    },
    {
        "message": "現段階で鳴海にヴィヴィの姿は見えていないし、声も届いていない。"
    },
    {
        "name": "【ヴィヴィ】",
        "message": "「――――確か」"
    },
    {
        "message": "地面を蹴ったことにも気づかないほど“軽い”跳躍。"
    },
    {
        "message": "埃に息を吹きかけたような重量感のない浮かび方で桁外れな高さまで跳び上がった。"
    },
    {
        "name": "【ヴィヴィ】",
        "message": "「ここでするものだったか――」"
    },
    {
        "message": "俺は見逃さぬよう首を上げて、そして下げた。ヴィヴィは一切手をつかわずに屋上の柵を越えていた。"
    },
    {
        "message": "全身が総毛だった。"
    },
    {
        "name": "【瑠依】",
        "message": "「あ、の、バカ……ッ！」"
    },
    {
        "name": "【鳴海】",
        "message": "「だから、誰と話してんだおめぇは」"
    },
    {
        "message": "一歩踏み外せば校庭へ真っ逆さま。そんな頼りない足場に立つヴィヴィは。けれど何の危なげもなく涼しげな無表情。"
    },
    {
        "message": "逆にこっちは冷たい汗が噴き出して、平常心が遠くの地へ旅行中だ。"
    },
    {
        "name": "【瑠依】",
        "message": "「そこを動くなよ……」"
    },
    {
        "message": "大声を出せば驚いて堕ちる危険性が高い。"
    },
    {
        "message": "俺は一歩一歩、噛み締めるようにして近づく。"
    },
    {
        "name": "【瑠依】",
        "message": "「（どうしてこうなった……）」"
    },
    {
        "message": "距離は近いが、柵の向こう側という隔たりがある以上うかつに手は伸ばせない。"
    },
    {
        "message": "ぼんやりと空を仰ぐヴィヴィに嫌な予感をおぼえる。"
    },
    {
        "name": "【ヴィヴィ】",
        "message": "「――そうか」"
    },
    {
        "message": "風にそっと押されるように、ヴィヴィはゆっくりと、何の支えもない“後ろ”に倒れこんでいく。"
    },
    {
        "message": "ピンと張った糸のような緊張感が、そのまま凍結した。"
    },
    {
        "name": "【ヴィヴィ】",
        "message": "「なるほどな――」"
    },
    {
        "message": "誰に贈るでもない拍手を、１、２、３回。"
    },
    {
        "name": "【ヴィヴィ】",
        "message": "「叩けば叩くほど、身体が風に乗る――」"
    },
    {
        "message": "――４、５、６回。"
    },
    {
        "name": "【ヴィヴィ】",
        "message": "「どこまでも続く青空に祝福される――」"
    },
    {
        "message": "――７、８、９回。"
    },
    {
        "name": "【ヴィヴィ】",
        "message": "「馬鹿にしては、考えられた遊びだ――」"
    },
    {
        "name": "【瑠依】",
        "message": "「――――柵をつかめぇえええぇぇえぇぇぇっ！！」"
    },
    {
        "message": "心から叫んだ。駆け出した。すでに遅かった。"
    },
    {
        "message": "１２回――ヴィヴィは手を叩きながら、真っ逆さまに落ちていった。"
    },
    {
        "name": "【鳴海】",
        "message": "「どうしたんだよ！　瑠依！　危ねぇぞ、やめとけっ！」"
    },
    {
        "message": "わずかに校舎が揺れる。"
    },
    {
        "message": "ヒト一人分の落下音。"
    },
    {
        "message": "地表に叩きつけられたヴィヴィを想像する。"
    },
    {
        "message": "キモチワルイ。目を背けたくなる。"
    },
    {
        "message": "それでも俺は機械的に柵から顔を出す。"
    },
    {
        "message": "血溜まりの中で潰れた蛙のようになった想像のヴィヴィを振り払い、グラウンドに目を凝らす。"
    },
    {
        "message": "想像していた悲惨な光景はどこにもなかった。"
    },
    {
        "name": "【鳴海】",
        "message": "「おいっ！！」"
    },
    {
        "message": "無理矢理に肩をつかまれ、振り向かされた。"
    },
    {
        "name": "【瑠依】",
        "message": "「……バードウォッチングだよ」"
    },
    {
        "name": "【鳴海】",
        "message": "「はぁ？」"
    },
    {
        "name": "【瑠依】",
        "message": "「珍しい鳥が飛んでたんだ。鳴海は目が悪いのかな？　見えなくて残念だね」"
    },
    {
        "name": "【鳴海】",
        "message": "「わかった、おめぇは正常だ。だからこっち来て少し休め、ちょっと横になれ。な？」"
    },
    {
        "name": "【瑠依】",
        "message": "「死をつかさどる鳥は堕ちていったよ」"
    },
    {
        "name": "【鳴海】",
        "message": "「黙って放課後まで寝てろ」"
    },
    {
        "name": "【瑠依】",
        "message": "「鳴海の膝枕は遠慮させてもらうけど……」"
    },
    {
        "message": "鳴海に言われるまま仰向けになると、背中の熱が奪われていく。"
    },
    {
        "message": "風は涼しく、空は青くて、気持ちいい。"
    },
    {
        "message": "蝕むように全てを照らす日差しだけが日陰者の俺には眩しすぎて、太陽が雲に隠れるのを待った。"
    },
    {
        "message": "結局、授業にも読書にも集中できないまま下校となった。"
    },
    {
        "message": "先に教室にもどった鳴海の情報いわく、あの震度２ほどの短い揺れは、校舎内にいたほとんどの人が感知していたらしい。"
    },
    {
        "name": "【鳴海】",
        "message": "「こんどは相撲部……はぁ。やるかっつーの屠ンぞ馬鹿ヤロウ」"
    },
    {
        "message": "鳴海は紙をぐしゃぐしゃに丸めてポケットにつっこんでいた。"
    },
    {
        "message": "きっと勧誘のチラシだろう。"
    },
    {
        "message": "鳴海のなりはこんなだからみんな直接は怖くて言えないが、どの部も鳴海の運動神経を買っている。"
    },
    {
        "name": "【瑠依】",
        "message": "「どうせ時間を持て余してるんだったら、ちゃんこ鍋食べ放題にチャレンジしてみれば？」"
    },
    {
        "name": "【鳴海】",
        "message": "「縛り付けられるのは性に合わねぇ。オレは自由に漂う雲になりてぇ」"
    },
    {
        "name": "【瑠依】",
        "message": "「明確な目標がないのが明確な分、鳴海は何か見つけたら一直線な気がする」"
    },
    {
        "message": "そこへいくと俺には何があるんだろう。"
    },
    {
        "message": "人の考えや裏側が“視える”だけの、バイト少年。"
    },
    {
        "message": "部活の勧誘なんてされたことないし、誰かに頼られたこともない。"
    },
    {
        "name": "【瑠依】",
        "message": "「そのうち真剣に打ち込めることが見つかるよ。気長に待とう」"
    },
    {
        "message": "鳴海に言い聞かせているようで、自分に言っているような気がした。"
    },
    {
        "message": "そして俺が俺である決定的な何かは、きっとヴィヴィが握っているのではないかとも、思った。"
    },
    {
        "name": "【鳴海】",
        "message": "「てめぇに泣き土下座を味合わせることしか考えらンねーよ」"
    },
    {
        "name": "【瑠依】",
        "message": "「付き合いきれないからやめてくれ」"
    },
    {
        "name": "【歩】",
        "message": "「ぽぽぽぽ〜〜〜〜ん！」"
    },
    {
        "name": "【鳴海】",
        "message": "「おおっと道端にどでけぇタケノコが生えてきやがったぞ。あぶねぇから引っこ抜いとくか」"
    },
    {
        "name": "【歩】",
        "message": "「なー！　やめろー！　さわーんなー！　持ち上げんなー！」"
    },
    {
        "name": "【鳴海】",
        "message": "「このゴツゴツした男みたいなさわり心地はなんだろぉなぁ」"
    },
    {
        "name": "【歩】",
        "message": "「あゆはごつごつじゃないー！　やわやわぷにぷにだー！　降ろせっての、くのくのっ！」"
    },
    {
        "name": "【鳴海】",
        "message": "「なんだ歩か。どーりで重いわけだわ！　ツァハハハハハ！！」"
    },
    {
        "name": "【歩】",
        "message": "「重くないよ、普通だよ！　おのれ鳴海めぇ……油断も隙もあったりなかったりっ！」"
    },
    {
        "name": "【瑠依】",
        "message": "「とんだセクハラを受けたな」"
    },
    {
        "message": "着衣の乱れを直す歩を手伝い、めくれ上がったカーディガンに手をかけた。"
    },
    {
        "message": "必然的に腰に触れることになるが、歩に対して余計な感情を差し挟まない自信があった。"
    },
    {
        "name": "【歩】",
        "message": "「ありがとお兄ちゃん。お兄ちゃんは紳士だね」"
    },
    {
        "message": "いつまでも兄と慕われる存在であるために、妹を異性として見てはならない。"
    },
    {
        "name": "【瑠依】",
        "message": "「歩は持ち上げられるより、頭ぽふぽふが好きだよな」"
    },
    {
        "name": "【歩】",
        "message": "「お兄ちゃんまでからかわないでっ！　変態金髪ピアスは半径１０Ｍ以内に入って来るな」"
    },
    {
        "name": "【鳴海】",
        "message": "「だったら１０Ｍ外から物干し竿かなんかでつついてやらぁ」"
    },
    {
        "name": "【歩】",
        "message": "「聞いたお兄ちゃん！　あいつ最低だよ！　一体何分の一の確率であーいう悪魔は生まれるんだろう」"
    },
    {
        "name": "【鳴海】",
        "message": "「ごちゃごちゃうるせーぞガキンチョ。オレの事を待ち伏せしてたことならバレてんだよ」"
    },
    {
        "name": "【歩】",
        "message": "「待ってない、全然待ってない！　待ってたのはこっち。お兄ちゃんの方」"
    },
    {
        "name": "【瑠依】",
        "message": "「俺と一緒に帰りたかったのか？」"
    },
    {
        "name": "【歩】",
        "message": "「実はあゆ、お兄ちゃんが今日バイト休みって知ってるんだー。遊びに行かない？」"
    },
    {
        "name": "【鳴海】",
        "message": "「ンだよ、しゃーねぇなドちくしょう。暇してんなら横浜でも流しに行くかぁ？」"
    },
    {
        "name": "【歩】",
        "message": "「お兄ちゃんどうしよう、暴走族にナンパされた。あゆ怖い」"
    },
    {
        "name": "【鳴海】",
        "message": "「だったらお得意の神様ちゃんにおねだりしてみろよ？　泣きながら助けてくださぁいってな」"
    },
    {
        "name": "【瑠依】",
        "message": "「歩、身に危険を感じたら迷わずイチイチマルだぞ」"
    },
    {
        "name": "【歩】",
        "message": "「もしもし、○察の皆々様お疲れのところ申し訳ないです事件です」"
    },
    {
        "name": "【鳴海】",
        "message": "「マジで電話してんじゃねぇだろうなおい！？」"
    },
    {
        "name": "【歩】",
        "message": "「顔からして犯罪者予備軍の柄悪い少年が――あゆのこと刺しましたっ！！」"
    },
    {
        "name": "【鳴海】",
        "message": "「捏造してんなザケんな屠ンぞ！？」"
    },
    {
        "name": "【瑠依】",
        "message": "「鳴海の場合、過去の犯罪歴根掘り葉掘りされたら３アウト人生チェンジかな」"
    },
    {
        "name": "【鳴海】",
        "message": "「やめろガキ。一端落ち着け、オレが代わるから携帯貸せ」"
    },
    {
        "name": "【歩】",
        "message": "「うぇへへ、嘘電だったり」"
    },
    {
        "name": "【鳴海】",
        "message": "「……ほぉ？」"
    },
    {
        "name": "【歩】",
        "message": "「引っかかった引っかかった！！　捕まって丸刈りにされてしまえ！　鳴海なんか大嫌いだ！」"
    },
    {
        "name": "【瑠依】",
        "message": "「こらあゆ。鳴海はムチャはするけど悪さはしてないだろ？」"
    },
    {
        "name": "【歩】",
        "message": "「ふふん、いつものお返しだよ。あゆをからかう鳴海は敵だっ！」"
    },
    {
        "name": "【鳴海】",
        "message": "「オラオラオラ、よそ見は禁物だぜぇー！？」"
    },
    {
        "name": "【歩】",
        "message": "「おわわっ、わーー！　わーー！！」"
    },
    {
        "name": "【鳴海】",
        "message": "「タッチパネルタッチパネル！」"
    },
    {
        "name": "【歩】",
        "message": "「やめろー、髪がくちゃくちゃになるーっ！　オシャレなあゆよ何処へ行くー！？」"
    },
    {
        "name": "【瑠依】",
        "message": "「あーあー……キミってやつは仮にも女の子の髪を……」"
    },
    {
        "name": "【鳴海】",
        "message": "「ツァハハハハハ！！　見ろよ瑠依、傑作だぜ。歩の頭で遊ぶとスカッとすんなー」"
    },
    {
        "name": "【歩】",
        "message": "「うぅ〜〜！　うぅ〜〜〜！　悪魔ぁぁ〜〜！　金髪悪魔ぁぁぁ〜！」"
    },
    {
        "message": "その場にかがみこんだ歩は、泣きべそを掻きながらせかせかと手鏡で髪を直しだした。"
    },
    {
        "name": "【歩】",
        "message": "「天清浄、地清浄、内外清浄、六根清浄……この穢れきった妖怪・金髪ピアスを祓給え、清め給え……っ！！」"
    },
    {
        "name": "【鳴海】",
        "message": "「おぉ怖。なんだなんだ？　本格的にオレとヤりあおうってのか？」"
    },
    {
        "name": "【歩】",
        "message": "「之、即ち、巫女魂ッ！！」"
    },
    {
        "name": "【歩】",
        "message": "「――――ふぅ。直った」"
    },
    {
        "message": "髪をセットするための言葉にしては大袈裟だった。"
    },
    {
        "name": "【歩】",
        "message": "「直ったんだけど？」"
    },
    {
        "name": "【鳴海】",
        "message": "「だなぁ」"
    },
    {
        "name": "【歩】",
        "message": "「ふざけんな、なんか言え！　かわいいとか好きとか言え！　大嫌いって返してあげるからっ！！」"
    },
    {
        "name": "【鳴海】",
        "message": "「直ったところで乳臭さは抜けねぇわな。いつになったらオレにふさわしい女になるのやら」"
    },
    {
        "name": "【歩】",
        "message": "「そんなもんなるかー！　うぅ〜〜！　わたしの頭ヘンじゃないって言えー！　ほめろー！」"
    },
    {
        "message": "ぽんっ。"
    },
    {
        "name": "【歩】",
        "message": "「ほぁ……お兄ちゃん……この手はなんだったり……？」"
    },
    {
        "name": "【瑠依】",
        "message": "「歩の頭はヘンなんかじゃないよ」"
    },
    {
        "name": "【歩】",
        "message": "「あゆの頭、タッチパネルじゃない？」"
    },
    {
        "name": "【瑠依】",
        "message": "「あたりまえだろ」"
    },
    {
        "message": "ふさふさのやわやわの髪は撫でているだけで安らいだ。"
    },
    {
        "name": "【瑠依】",
        "message": "「制服も着こなしてる、どこに出しても恥ずかしくない女の子だ」"
    },
    {
        "name": "【歩】",
        "message": "「ふへへ、なんだよぉ、褒めるなよぉ、この第一級フラグ建築士がぁ」"
    },
    {
        "name": "【瑠依】",
        "message": "「言葉遣いは、ちゃんとしような」"
    },
    {
        "name": "【歩】",
        "message": "「ちゃんとしてるよ！　普通だよ！　へへ♪」"
    },
    {
        "message": "その屈託のない笑顔には人の心を綺麗にする洗浄機能が備わっている。"
    },
    {
        "message": "俺にとっての秘密の癒し系。大切な妹分。心からほっこりし合える、そんな仲。"
    },
    {
        "message": "時に騒がしく思うこともあるが、そんな個性もひっくるめて付き合っていける。"
    },
    {
        "name": "【瑠依】",
        "message": "「さて、ちゃんと女の子してる歩にはおいしいものをご馳走しなきゃな」"
    },
    {
        "name": "【歩】",
        "message": "「ティーボーンステーキッ！　あゆは今、無性にティーボーンステーキが食べたいっ！！」"
    },
    {
        "name": "【鳴海】",
        "message": "「んじゃオレも同じヤツ５００ｇで頼むわ」"
    },
    {
        "name": "【瑠依】",
        "message": "「そんなにがっつり食べたら夕飯入らないぞ歩。それでもいいのか？」"
    },
    {
        "name": "【歩】",
        "message": "「うん。良い！　お兄ちゃんのおごり♪」"
    },
    {
        "name": "【瑠依】",
        "message": "「鳴海、『ＷＩＮ』に行こう、歩は来ないってさ」"
    },
    {
        "name": "【歩】",
        "message": "「やっやっやっ、行くともだよ？　でも、サータアンダギーくらいなら……良かったり……？」"
    },
    {
        "name": "【瑠依】",
        "message": "「まったく。制服に付かないようにするんだぞ」"
    },
    {
        "name": "【歩】",
        "message": "「わーい、やったね！　気が変わったら嫌だから先に行って席取っておくよ」"
    },
    {
        "message": "てってけてーと走り去る歩。"
    },
    {
        "name": "【鳴海】",
        "message": "「あのガキだきゃぁ、世界が真っ黒に腐りきって沼みてぇに泡だっても元気にはしゃぎ回りそうな気がするぜ」"
    },
    {
        "name": "【瑠依】",
        "message": "「なにそれ。歩を褒めてるのか？」"
    },
    {
        "name": "【鳴海】",
        "message": "「違ぇよ、とっとと行こうぜ。待たせたらわりぃだろ？」"
    },
    {
        "message": "妙なところで神経質な鳴海だった。"
    },
    {
        "name": "【歩】",
        "message": "「ちゅうぅ〜〜〜〜〜、ぷぁ。生き返ったー」"
    },
    {
        "name": "【鳴海】",
        "message": "「ずずず。ごち！」"
    },
    {
        "name": "【瑠依】",
        "message": "「二人とも飲み終わるの早すぎ。おしゃべりとの配分を考えてないだろ？」"
    },
    {
        "name": "【鳴海】",
        "message": "「コーヒーは一杯頼めばおかわり自由だぜ？」"
    },
    {
        "name": "【歩】",
        "message": "「オレンジジュースだって半分飲んで水で薄めて、また半分飲んで水で薄めれば無限に飲めるよ」"
    },
    {
        "name": "【鳴海】",
        "message": "「な？　な？　こういうこと平気で言えるアメーバ並の脳みそなんだぜコイツは」"
    },
    {
        "name": "【歩】",
        "message": "「アメーバってなに？　美味しいの？」"
    },
    {
        "name": "【瑠依】",
        "message": "「考え方が極端に一面的で単純だけど、そんなキミが好きだっていう告白の言葉だよ」"
    },
    {
        "name": "【歩】",
        "message": "「なー！　なー！！？」"
    },
    {
        "name": "【歩】",
        "message": "「あゆ告白されたら困っちゃうよ！　ゴールドヘアーの人はお断りしてるんだよ！」"
    },
    {
        "name": "【鳴海】",
        "message": "「瑠依おめぇ適当コくなよ！　とにかく、薄めて無限に飲めるのはカル〇スの特権だっつーの」"
    },
    {
        "name": "【歩】",
        "message": "「お兄ちゃんと話すな金山頭！　喰らえデビルズソルト！　フッ！」"
    },
    {
        "name": "【鳴海】",
        "message": "「がぁぁっ、目に染みるぜぇ……！　ならこっちは九州の塩だオラァ！」"
    },
    {
        "name": "【歩】",
        "message": "「どわぁっ！？」"
    },
    {
        "name": "【瑠依】",
        "message": "「雪合戦ならぬ塩合戦か」"
    },
    {
        "name": "【歩】",
        "message": "「くぬぬぅ、直接振り掛けるとはなんて乱暴な男だ！」"
    },
    {
        "name": "【鳴海】",
        "message": "「んな、チマチマ掌に塩振って、フッ！　なんて女々しいことしてられっかオラオラ！！」"
    },
    {
        "name": "【歩】",
        "message": "「くぅ〜〜〜〜！　あゆの頭に塩振るなー！！　下味付けするなー！！」"
    },
    {
        "name": "【鳴海】",
        "message": "「お、ケーキの付け合せで瑠依の抱き枕がついてくるんだってよ」"
    },
    {
        "name": "【歩】",
        "message": "「お兄ちゃん抱き枕欲しいっ！　夜のお供にお兄ちゃん抱き枕――――ハッ！？？」"
    },
    {
        "name": "【瑠依】",
        "message": "「あ、歩、そんな物があったとして、どうする気だよ……」"
    },
    {
        "name": "【歩】",
        "message": "「ま、跨ったり……ハグしたり……と、と、とか？」"
    },
    {
        "name": "【瑠依】",
        "message": "「……お、俺の……歩像が…………」"
    },
    {
        "name": "【歩】",
        "message": "「な、なーーーんてね！　鳴海に付き合っただけなのだっ！　わ、ワハハ！　ワハハハハ！」"
    },
    {
        "name": "【鳴海】",
        "message": "「すげぇ動揺してるじゃん。こいつバカだわ。この店、バカ割引ってねぇのか？　店員さーん」"
    },
    {
        "name": "【歩】",
        "message": "「滅殺……ッ！！！」"
    },
    {
        "name": "【瑠依】",
        "message": "「少し静かにしてくれ。あゆ、楊枝を目に刺そうとしない！　鳴海も、その手のコーヒーをどうする気だ！」"
    },
    {
        "name": "【声】",
        "message": "「……くふ、くしくし……」"
    },
    {
        "name": "【瑠依】",
        "message": "「…………？」"
    },
    {
        "message": "特徴的な含み笑いが、俺の意識を隣テーブルに向かせた。"
    },
    {
        "name": "【少女】",
        "message": "「くしし……ユーモアあふれる方々ですね……」"
    },
    {
        "message": "独特な笑い方なのにちっともおかしく聴こえない。"
    },
    {
        "message": "天使の歌声のように澄んだ声は人を魅了するだけのものがあった。"
    },
    {
        "name": "【鳴海】",
        "message": "「おいおい瑠依、今の聞いたか？　隣の外人がこっち見たぞ」"
    },
    {
        "name": "【瑠依】",
        "message": "「気になるなら話しかけてみれば？」"
    },
    {
        "message": "とはいえ、目を引くのはあたりまえだろう。"
    },
    {
        "message": "雑誌でしかお目にかかれない嘘くさいプロポーション。"
    },
    {
        "message": "余裕のある大人びた微笑をたたえた白人スマイルは芸術の域に達している。"
    },
    {
        "name": "【鳴海】",
        "message": "「イイトコのお嬢様かね……」"
    },
    {
        "message": "ぼやく鳴海の意見に相違はなく、気品漂う姿は一般家庭にありがちな隙が見当たらなかった。"
    },
    {
        "message": "気になる所と言えば、片目をすっぽり覆い隠す眼帯だろうか。"
    },
    {
        "message": "ファッションの一つとして機能するそれは消耗品には見えないが、純粋に片目にハンデを背負って生きているのかもしれない。"
    },
    {
        "name": "【瑠依】",
        "message": "「店の中だし、ただでさえキミ達の声は響くんだ。あゆも鳴海も、もう少し静かにな」"
    },
    {
        "name": "【歩】",
        "message": "「むぅ、お兄ちゃんはあーいうのがタイプなの？」"
    },
    {
        "name": "【瑠依】",
        "message": "「だから、もう彼女の事を言うのはやめるんだ。迷惑がられるよ」"
    },
    {
        "name": "【鳴海】",
        "message": "「制服を着てるってことは俺たちと大差ない年齢ってことだ。比べて歩の色気なさと来たらイヤになるぜ」"
    },
    {
        "name": "【歩】",
        "message": "「なー！　そのため息はなんだー！！」"
    },
    {
        "message": "ダメだこの人たち、何も聞いてない。"
    },
    {
        "name": "【歩】",
        "message": "「あゆは何を隠そう、美少女コンテスト上位入賞者でもあるんだよ？」"
    },
    {
        "name": "【鳴海】",
        "message": "「いつ？　どこで？　地球が何回まわったときの話だ？　審査員は森のクマやリスかなんかか？」"
    },
    {
        "name": "【歩】",
        "message": "「ちゃんとしたコンテストだもん！　この欲張りボディがその証拠だっ！」"
    },
    {
        "message": "歩は姿勢が良いので、ただでさえ主張の激しい胸がつんと前に突き出される。"
    },
    {
        "name": "【歩】",
        "message": "「どうだ参ったか！？　更衣室で友達に羨ましがられることだってあったりするんだよ？」"
    },
    {
        "message": "柔らか素材のカーディガンにくっきりと浮かび上がった女性の証は、平均以上の大きさを誇る。"
    },
    {
        "name": "【瑠依】",
        "message": "「ああ、歩は健康に育ってる。もうすっかり大人の身体だな。だから静かにしような？」"
    },
    {
        "name": "【歩】",
        "message": "「え、えへへ……ほら鳴海、お兄ちゃんはすでにメロメロだよ？　君もあゆの虜ではないのかね？」"
    },
    {
        "name": "【少女】",
        "message": "「くし……くしし……。元気な子ですね」"
    },
    {
        "message": "笑われてる。静かにしようよ……。"
    },
    {
        "name": "【鳴海】",
        "message": "「わかってねぇなぁ歩は。大人っぽさってのはオーラなんだよ。がきんちょの胸がＥカップだろうがＺカップだろうが関係ねぇわけだ」"
    },
    {
        "name": "【歩】",
        "message": "「――――ッ！！？」"
    },
    {
        "message": "ボン！　と歩の小顔が唐辛子のように赤く発火した。"
    },
    {
        "name": "【歩】",
        "message": "「〜〜〜！　〜〜〜！！　〜〜〜！！！」"
    },
    {
        "message": "胸を隠すように手を交差させると、跳び引く。“変質者です！”と言わんばかりに鳴海を指差した。"
    },
    {
        "message": "ひとまず俺は正面に立ち、手を握って落ち着かせることにした。"
    },
    {
        "name": "【瑠依】",
        "message": "「どうしたのか言ってみなよ」"
    },
    {
        "name": "【歩】",
        "message": "「知ってる……鳴海があゆの……あゆの……」"
    },
    {
        "name": "【瑠依】",
        "message": "「歩のなにを？」"
    },
    {
        "message": "耳を寄せると、俺の服をつかむ力が強まる。身体の色んなところがペタペタぶつかった。"
    },
    {
        "name": "【歩】",
        "message": "「……ごにょごにょ…………を……」"
    },
    {
        "name": "【瑠依】",
        "message": "「ん？」"
    },
    {
        "name": "【歩】",
        "message": "「……限りなくＦに近いＥ……だったり」"
    },
    {
        "message": "鳴海の口からでまかせのカップ数がたまたま当たっていたのか。"
    },
    {
        "message": "……こうしてみると大きいんだな歩。"
    },
    {
        "name": "【歩】",
        "message": "「お兄ちゃん……？」"
    },
    {
        "name": "【瑠依】",
        "message": "「あ、いや――」"
    },
    {
        "message": "イケナイ思考を捨て、密着しきった身体に隙間を作る。"
    },
    {
        "name": "【瑠依】",
        "message": "「鳴海が馬鹿言っただけだろ。気にしたら逆に感付かれるから。な？」"
    },
    {
        "name": "【歩】",
        "message": "「う、うん……あゆ、取り乱しすぎたかも……」"
    },
    {
        "message": "取り乱したのは俺の方だと思う。感情のふり幅は狭い方だと自己分析していたが、案外脆いものだ。"
    },
    {
        "name": "【瑠依】",
        "message": "「鳴海」"
    },
    {
        "name": "【鳴海】",
        "message": "「鳴海だが？」"
    },
    {
        "name": "【瑠依】",
        "message": "「舌出すなよ」"
    },
    {
        "name": "【鳴海】",
        "message": "「――イデッ！　ってぇなおい。ひ、ひた、かんらひゃれぇはぁ！」"
    },
    {
        "name": "【瑠依】",
        "message": "「叩くから舌出すなって言ったんだよ。コーヒー染みるぞ」"
    },
    {
        "name": "【歩】",
        "message": "「いい気味だバーカ」"
    },
    {
        "name": "【少女】",
        "message": "「くしし……おもしろい人たち。ああ……とても素敵なティータイム……モスクワ郊外の夕べのよう」"
    },
    {
        "message": "優雅にカップに口付ける美少女。完全にパフォーマンスだと勘違いされているな。"
    },
    {
        "name": "【鳴海】",
        "message": "「とにかくだ、オレンジジュースなんてガキ界を代表する飲み物をたしなむようじゃ甘い甘い」"
    },
    {
        "name": "【歩】",
        "message": "「だったら何を飲めば大人なの」"
    },
    {
        "name": "【少女】",
        "message": "「…………♪　くせのない良い香り……」"
    },
    {
        "name": "【鳴海】",
        "message": "「ああして紅茶の香りを愉しみながらゆったりと過ごすわけだ。幼稚なおめぇにはマネできまい」"
    },
    {
        "name": "【歩】",
        "message": "「うぐぐぐ、鳴海め……言わせておけばぁ……！」"
    },
    {
        "name": "【少女】",
        "message": "「抹茶ミルクのミルク抜き。注文してみるものですね……♪」"
    },
    {
        "name": "【歩】",
        "message": "「――抹茶じゃん！　それただの抹茶じゃん！　大人の嗜みにしては渋すぎるよ！」"
    },
    {
        "name": "【鳴海】",
        "message": "「これ見よがしに連呼すんなっ。たまたま抹茶を飲みたい風流な気分だったんだ、そうに違いねぇ！」"
    },
    {
        "name": "【瑠依】",
        "message": "「他人の飲み物をとやかく言うキミらはどっちもガキだよっ」"
    },
    {
        "name": "【少女】",
        "message": "「くふっ……ふくく、くしし、おもしろいですねローザ」"
    },
    {
        "message": "まるで誰かに話しかけているようだった。"
    },
    {
        "name": "【少女】",
        "message": "「このカフェもここに来るお客様も、イリーナのお気に入りです」"
    },
    {
        "message": "イリーナ？　ローザ？"
    },
    {
        "message": "脈絡からするとイリーナが彼女の一人称だろう。"
    },
    {
        "message": "だとするならローザとは誰の名前だろうか……？"
    },
    {
        "name": "【イリーナ】",
        "message": "「ローザのお口には合いましたか？」"
    },
    {
        "message": "………………。"
    },
    {
        "message": "…………いや、まさかな……。"
    },
    {
        "name": "【鳴海】",
        "message": "「なぁ、今のってよぉ……」"
    },
    {
        "name": "【歩】",
        "message": "「もしかして…………人形に話しかけて……たり？」"
    },
    {
        "message": "目を背けるのも、気づかないフリをするのも、この際ナシにしよう。"
    },
    {
        "message": "精巧な人形のような制服美少女の隣には、本物の“人形”が座っている。"
    },
    {
        "name": "【イリーナ】",
        "message": "「ローザ…………♪　……ふ……くし………………」"
    },
    {
        "name": "【イリーナ】",
        "message": "「…………………………（ぶつぶつぶつぶつぶつぶつぶつぶつぶつぶつ）」"
    },
    {
        "name": "【歩】",
        "message": "「あわわわわわわ……！」"
    },
    {
        "name": "【イリーナ】",
        "message": "「…………………………（ぶつぶつぶつぶつぶつぶつぶつぶつぶつぶつ）」"
    },
    {
        "message": "この手の人種だったとは……。"
    },
    {
        "name": "【鳴海】",
        "message": "「顔を伏せろ歩」"
    },
    {
        "name": "【歩】",
        "message": "「何をする鳴海ぃっ！」"
    },
    {
        "name": "【鳴海】",
        "message": "「こりゃぁ不良暦＝年齢のオレの勘だが、あいつぁヤバイ。きっと、聖うんちゃら学院きっての暴君とか言われてるに違いねぇ」"
    },
    {
        "message": "平凡な人生を送るなら極力避けて通るべき人物という認識は、俺も抱いていた。"
    },
    {
        "name": "【イリーナ】",
        "message": "「くしし……こんなに輝いて、まだ足りないんですか？　欲張りなローザ。帰ったらエーゲ海よりも美しい艶の髪をイヤってほど梳いてあげますね」"
    },
    {
        "name": "【イリーナ】",
        "message": "「イリーナより心からの愛を込めて……ちゅぅ♪　んぅ〜〜♪」"
    },
    {
        "name": "【歩】",
        "message": "「ひぃ……！　チューした！　にににに人形と……！」"
    },
    {
        "name": "【瑠依】",
        "message": "「歩、あれは彼女の所有物。つまり彼女の勝手だよな？　だから大人しくしような？」"
    },
    {
        "name": "【歩】",
        "message": "「うん。あゆ、言う通りにする。あゆはなにも見てないよ。本当だよ」"
    },
    {
        "message": "趣味は人それぞれ。個性は独特なほど際立つ。だから俺は彼女を否定しない。"
    },
    {
        "name": "【イリーナ】",
        "message": "「レストルームに行って来ますね。大丈夫、一人で行けますよ。ローザは心配性ですね」"
    },
    {
        "message": "だけど――個性の強い人間は裏に秘めているものも計り知れない。"
    },
    {
        "message": "警戒するにこしたことはない。歩にもしもの事があってからでは遅い。"
    },
    {
        "name": "【鳴海】",
        "message": "「ふぅ、行ったか……トイレに行くのに人形の許可を取るなんざ考えらんねぇよ」"
    },
    {
        "name": "【歩】",
        "message": "「……はぁ…………こわかったぁ……」"
    },
    {
        "message": "今のうちに退散するべきだろう。"
    },
    {
        "message": "俺はアイスティを一気に飲み干した。"
    },
    {
        "name": "【イリーナ】",
        "message": "「――――戻りましたよローザ」"
    },
    {
        "name": "【イリーナ】",
        "message": "「……？　席は、こちらで合っていますね。ローザ？」"
    },
    {
        "name": "【イリーナ】",
        "message": "「ああ――くしし。そういうことですか。かくれんぼですね？　まったく、遊び好きなんですから」"
    },
    {
        "name": "【イリーナ】",
        "message": "「どこかしら？　ここかしら？」"
    },
    {
        "name": "【女性客】",
        "message": "「ちょ、ちょっとっ！　なんなのよ貴女いきなりっ！」"
    },
    {
        "name": "【イリーナ】",
        "message": "「くしし、失敗でした。ローザは隠れるのが上手ですね……」"
    },
    {
        "name": "【イリーナ】",
        "message": "「――こっちかしら？」"
    },
    {
        "name": "【男性客】",
        "message": "「なんだ突然っ！　人の鞄を勝手に開けるんじゃない！」"
    },
    {
        "name": "【イリーナ】",
        "message": "「ここにもいませんか……」"
    },
    {
        "name": "【イリーナ】",
        "message": "「…………ローザ？　……ローザどこ？」"
    },
    {
        "name": "【イリーナ】",
        "message": "「いない。いないいないいないローザいないローザどこローザいないローザどこローザ……」"
    },
    {
        "name": "【イリーナ】",
        "message": "「ローザがいないとイリーナはローザがいないとダメなのにローザだってイリーナがいないとダメなのにローザがいないなんてあるわけないあるわけない……」"
    },
    {
        "name": "【イリーナ】",
        "message": "「もしかして――――誰かが連れ去ったんじゃ……」"
    },
    {
        "message": "店を出たあと鳴海とはすぐに別れた。"
    },
    {
        "name": "【歩】",
        "message": "「お邪魔虫はもういないー。お兄ちゃんと二人っきりー。今日のご飯はなーんだったりー」"
    },
    {
        "message": "道の端に寄せられた小枝と落ち葉を踏み鳴らす歩は上機嫌だった。"
    },
    {
        "name": "【歩】",
        "message": "「あっ、そういえばお兄ちゃん。お昼前に校舎が揺れたのって気づいたかな？」"
    },
    {
        "name": "【瑠依】",
        "message": "「え――ああ、あれか」"
    },
    {
        "message": "興味津々とばかりに喰い付くと余計な詮索をされるかもしれない。"
    },
    {
        "message": "そっけなくも、続きを諭すように目を向ける。"
    },
    {
        "name": "【瑠依】",
        "message": "「地震だったのかな。ちゃんと余震に備えて机の下に隠れたか？」"
    },
    {
        "name": "【歩】",
        "message": "「一瞬のことだったから何もしてないよ。ただ揺れたのってあゆの教室からすっごい近かったんだよね」"
    },
    {
        "name": "【歩】",
        "message": "「みんな気になって仕方なかったみたいで、授業そっちのけで原因捜し」"
    },
    {
        "name": "【歩】",
        "message": "「結局、グラウンドで走ってた別のクラスの子が――『あゆあゆんとこの校舎の壁、穴開いてるよ』って教えてくれたんだ」"
    },
    {
        "name": "【瑠依】",
        "message": "「校舎の外壁に……穴……？」"
    },
    {
        "name": "【歩】",
        "message": "「うん。穴。このくらいの丸い穴が開いてたの」"
    },
    {
        "message": "親指と人差し指をくっつけて示す。"
    },
    {
        "name": "【歩】",
        "message": "「あーいうとこって、ちょっとやそっとじゃ穴なんて開かないよね。普通じゃないよ！」"
    },
    {
        "message": "柱にあたる部分の強化は頑健そのものだろう。"
    },
    {
        "message": "骨組みの鉄骨に行き届くほどだとしたら、その貫通力はライフル弾に匹敵する。"
    },
    {
        "message": "そんなことをできるのは……。"
    },
    {
        "name": "【瑠依】",
        "message": "「きっとスカイフィッシュの仕業だな」"
    },
    {
        "name": "【歩】",
        "message": "「スカイフィッシュ……ってなんだろう？」"
    },
    {
        "message": "歩が懸命にスカイフィッシュという言葉に考えをめぐらせている間に俺は別のことを考える。"
    },
    {
        "message": "――壁に穴を開けたのはヴィヴィだろう。"
    },
    {
        "message": "おそらくは突き刺したのは鎌の柄にあたる部分。落下速度を抑える為と考えるのが妥当なところか。"
    },
    {
        "message": "とはいえ、それがわかったところで、あんな去り方をした理由にはならない。"
    },
    {
        "message": "真相はヴィヴィの頭を割ってみなければ謎のまま――なんて、そんな比喩は不謹慎すぎるか。"
    },
    {
        "message": "しかし、逆を考えれば……屋上から落ちても死なない耐久性を持っているのであれば、減速する為の穴など開ける必要はあるのだろうか？"
    },
    {
        "message": "落ちても死なないなら、素直に落ちたのではないか？"
    },
    {
        "message": "あの場から居なくなっていたにせよ、屋上から落ちたヴィヴィに傷一つないとは言い切れないだろう。"
    },
    {
        "message": "様子を見に行かないとまずいか……。"
    },
    {
        "name": "【歩】",
        "message": "「お兄ちゃん、スカイフィッシュって何だったりするの？　知らないと普通じゃないかな？」"
    },
    {
        "name": "【瑠依】",
        "message": "「ごめん歩。コレ持って、先に帰っててもらえるか？」"
    },
    {
        "message": "走るのに邪魔な鞄を渡す。竹刀袋以外に余計なものは持ちたくなかった。"
    },
    {
        "name": "【歩】",
        "message": "「えー、お兄ちゃんどっか行くなんてダメなんだよ。あゆも行……く…………？」"
    },
    {
        "name": "【歩】",
        "message": "「あっ――あっ――――あああぁぁぁーーーっ！！」"
    },
    {
        "name": "【瑠依】",
        "message": "「なんだ、どうしたんだよ」"
    },
    {
        "name": "【歩】",
        "message": "「す、す、す、スカイフィッシュ出たぁぁーーーっ！！」"
    },
    {
        "message": "なバカな！　とさすがに突っ込みを入れたくなったが――"
    },
    {
        "message": "現実を知って、戦慄した。"
    },
    {
        "message": "それはスカイフィッシュなんて夢のある話ではない。"
    },
    {
        "name": "【瑠依】",
        "message": "「そんな馬鹿な……」"
    },
    {
        "message": "歩に手渡した鞄はチャックが開いていて、そこには“頭”があり生々しい“髪”が生えていた。"
    },
    {
        "message": "見間違いようのないお揃いの眼帯――“ＷＩＮ”で抹茶を嗜んでいた美少女が肩に乗せていた人形だった。"
    },
    {
        "name": "【瑠依】",
        "message": "「Ｂ級ホラーかよ……一体いつの間に……」"
    },
    {
        "name": "【歩】",
        "message": "「いつの間にって――」"
    },
    {
        "message": "あ、ヤバ。言ってからじゃ遅い。"
    },
    {
        "name": "【歩】",
        "message": "「お、お、お兄ちゃんが入れたんじゃないの……？　じゃあコレって、コレって……！」"
    },
    {
        "name": "【瑠依】",
        "message": "「落ち着けよ。ひとりでに動いて入るとか、そんなわけがないだろ？」"
    },
    {
        "message": "スポンジが水を吸うように、みるみるうちに歩の顔が青ざめていく。"
    },
    {
        "name": "【歩】",
        "message": "「じゃあ、じゃあ――コレは、正真正銘、ホンモノの……」"
    },
    {
        "name": "【歩】",
        "message": "「スカイフィッシュなんだぁああああああぁぁぁーーーーーっ！！！」"
    },
    {
        "name": "【瑠依】",
        "message": "「だからそれは違うって！！」"
    },
    {
        "name": "【歩】",
        "message": "「わぁああああぁぁああぁあぁああああああんっ！！」"
    },
    {
        "message": "鞄を振り回しながら一目散に走り出す歩。"
    },
    {
        "name": "【瑠依】",
        "message": "「おい――！」"
    },
    {
        "message": "歩の持った鞄が振り回されたことで、人形が見事な垂直ノックのように高々と放られた。"
    }
]